setup.py
launch/__init__.py
launch/launchtime.py
launch/line.py
launchTest.egg-info/PKG-INFO
launchTest.egg-info/SOURCES.txt
launchTest.egg-info/dependency_links.txt
launchTest.egg-info/requires.txt
launchTest.egg-info/top_level.txt