Metadata-Version: 2.1
Name: launchTest
Version: 0.0.2
Summary: APP Launch Test
Home-page: https://github.com/xiaoyaoamiao/lt.git
Author: bob
Author-email: miao2005du@163.com
License: MIT License
Keywords: launchtest
Platform: any
